egov_law_mcp/__init__.py
egov_law_mcp/server.py
egov_law_mcp/api/__init__.py
egov_law_mcp/api/client.py
egov_law_mcp/cache/__init__.py
egov_law_mcp/cache/manager.py
egov_law_mcp/models/__init__.py
egov_law_mcp/models/schemas.py
egov_law_mcp/parser/__init__.py
egov_law_mcp/parser/xml_to_markdown.py
egov_law_mcp/tools/__init__.py
egov_law_mcp/tools/article.py
egov_law_mcp/tools/fulltext.py
egov_law_mcp/tools/keyword.py
egov_law_mcp/tools/revisions.py
egov_law_mcp/tools/search.py
egov_law_mcp-0.1.0.dist-info/METADATA
egov_law_mcp-0.1.0.dist-info/WHEEL
egov_law_mcp-0.1.0.dist-info/entry_points.txt
egov_law_mcp-0.1.0.dist-info/licenses/LICENSE
egov_law_mcp-0.1.0.dist-info/RECORD
