Metadata-Version: 2.4
Name: egov-law-mcp
Version: 0.1.0
Summary: MCP Server for e-Gov Law API - Japanese law search and retrieval
Author: takurot
License-Expression: MIT
License-File: LICENSE
Keywords: api,egov,japan,law,mcp
Classifier: Development Status :: 3 - Alpha
Classifier: Intended Audience :: Developers
Classifier: License :: OSI Approved :: MIT License
Classifier: Programming Language :: Python :: 3
Classifier: Programming Language :: Python :: 3.10
Classifier: Programming Language :: Python :: 3.11
Classifier: Programming Language :: Python :: 3.12
Requires-Python: >=3.10
Requires-Dist: cachetools>=5.0.0
Requires-Dist: httpx>=0.27.0
Requires-Dist: lxml>=5.0.0
Requires-Dist: mcp>=1.0.0
Requires-Dist: pydantic>=2.0.0
Provides-Extra: dev
Requires-Dist: lxml-stubs>=0.5.0; extra == 'dev'
Requires-Dist: mypy>=1.10.0; extra == 'dev'
Requires-Dist: pytest-asyncio>=0.23.0; extra == 'dev'
Requires-Dist: pytest-cov>=4.0.0; extra == 'dev'
Requires-Dist: pytest>=8.0.0; extra == 'dev'
Requires-Dist: respx>=0.21.0; extra == 'dev'
Requires-Dist: ruff>=0.4.0; extra == 'dev'
